src/segment_scan8.v
`timescale 1ns/1ps

// Logical outputs are active-high. Apply board polarity in the wrapper.
// Each slot contains one active interval followed by one blank interval.
module segment_scan8 (
    input wire clk, rst, enable,
    input wire [31:0] digits,
    output reg [7:0] select,
    output reg [7:0] segments,
    output reg [2:0] index
);

    reg blank;
    reg [3:0] nibble;

    always @(posedge clk) begin
        if (rst) begin
            index <= 0;
            blank <= 1'b1;
        end else if (enable) begin
            blank <= ~blank;
            if (!blank) index <= index + 1'b1;
        end
    end

    always @* begin
        nibble = digits >> (index * 4);
        select = blank ? 8'h00 : (8'h01 << index);
        // abcdefg, dp; decimal point remains off.
        case (nibble)
            4'h0: segments = 8'b11111100;
            4'h1: segments = 8'b01100000;
            4'h2: segments = 8'b11011010;
            4'h3: segments = 8'b11110010;
            4'h4: segments = 8'b01100110;
            4'h5: segments = 8'b10110110;
            4'h6: segments = 8'b10111110;
            4'h7: segments = 8'b11100000;
            4'h8: segments = 8'b11111110;
            4'h9: segments = 8'b11110110;
            4'ha: segments = 8'b11101110;
            4'hb: segments = 8'b00111110;
            4'hc: segments = 8'b10011100;
            4'hd: segments = 8'b01111010;
            4'he: segments = 8'b10011110;
            4'hf: segments = 8'b10001110;
            default: segments = 8'h00;
        endcase
    end

endmodule

sim/tb_segment_scan8.sv
`timescale 1ns/1ps

module tb_segment_scan8;

reg clk = 0, rst = 1;
integer checks = 0;

always #5 clk = ~clk;

task step; begin @(posedge clk); #1; end endtask

task check(input condition, input [8*100-1:0] description);
begin
    checks = checks + 1;
    if (condition !== 1'b1) begin
        $display("LAB2_FAIL %0s time=%0t", description, $time);
        $fatal(1, "check failed");
    end
end
endtask

task finish;
begin
    $display("LAB2_PASS segment_scan8 checks=%0d", checks);
    $finish;
end
endtask

initial begin $dumpfile("wave.vcd"); $dumpvars(0, tb_segment_scan8); end
initial begin #100000; $fatal(1, "watchdog timeout"); end

reg enable = 0;
reg [31:0] digits = 32'h0;
wire [7:0] select, segments;
wire [2:0] index;

segment_scan8 dut(clk, rst, enable, digits, select, segments, index);

reg [7:0] expected[0:15];
integer bank, position, lap;

initial begin
    // Truth-table values, ordered 0..F with abcdefg and dp.
    expected[0]=8'hfc;  expected[1]=8'h60;  expected[2]=8'hda;  expected[3]=8'hf2;
    expected[4]=8'h66;  expected[5]=8'hb6;  expected[6]=8'hbe;  expected[7]=8'he0;
    expected[8]=8'hfe;  expected[9]=8'hf6;  expected[10]=8'hee; expected[11]=8'h3e;
    expected[12]=8'h9c; expected[13]=8'h7a; expected[14]=8'h9e; expected[15]=8'h8e;

    step; check(select === 0 && index === 0, "reset blanks digit zero"); rst = 0;

    for (bank = 0; bank < 2; bank = bank + 1) begin
        digits = bank ? 32'hfedcba98 : 32'h76543210;
        for (lap = 0; lap < 2; lap = lap + 1) begin
            for (position = 0; position < 8; position = position + 1) begin
                enable = 1; step;
                check(index === position, "position order");
                check(select === (1 << position), "exactly intended digit active");
                check(segments === expected[bank*8 + position], "hex truth table");

                enable = 0; step;
                check(select === (1 << position), "enable zero holds active slot");

                enable = 1; step;
                check(select === 0, "blank interval between every digit");

                enable = 0; step;
                check(select === 0, "blank interval hold");
            end
        end
    end

    enable = 1; step; rst = 1; step;
    check(select === 0 && index === 0, "reset from active scan");
    finish;
end

endmodule

evidence/08/vscode/wave.vcd
$date
	Wed Sep 16 18:41:27 2026
$end
$version
	Icarus Verilog
$end
$timescale
	1ps
$end
$scope module tb_segment_scan8 $end
$var wire 8 ! select [7:0] $end
$var wire 8 " segments [7:0] $end
$var wire 3 # index [2:0] $end
$var reg 1 $ clk $end
$var reg 32 % digits [31:0] $end
$var reg 1 & enable $end
$var reg 1 ' rst $end
$var integer 32 ( bank [31:0] $end
$var integer 32 ) checks [31:0] $end
$var integer 32 * lap [31:0] $end
$var integer 32 + position [31:0] $end
$scope module dut $end
$var wire 1 $ clk $end
$var wire 32 , digits [31:0] $end
$var wire 1 & enable $end
$var wire 1 ' rst $end
$var reg 1 - blank $end
$var reg 3 . index [2:0] $end
$var reg 4 / nibble [3:0] $end
$var reg 8 0 segments [7:0] $end
$var reg 8 1 select [7:0] $end
$upscope $end
$scope task check $end
$var reg 1 2 condition $end
$var reg 800 3 description [799:0] $end
$upscope $end
$scope task finish $end
$upscope $end
$scope task step $end
$upscope $end
$upscope $end
$enddefinitions $end
$comment Show the parameter values. $end
$dumpall
$end
#0
$dumpvars
bx 3
x2
bx 1
bx 0
bx /
bx .
x-
b0 ,
bx +
bx *
b0 )
bx (
1'
0&
b0 %
0$
bx #
bx "
bx !
$end
#5000
b11111100 "
b11111100 0
b0 !
b0 1
b0 /
1-
b0 #
b0 .
1$
#6000
1&
b0 +
b0 *
b1110110010101000011001000010000 %
b1110110010101000011001000010000 ,
b0 (
0'
b1 )
b111001001100101011100110110010101110100001000000110001001101100011000010110111001101011011100110010000001100100011010010110011101101001011101000010000001111010011001010111001001101111 3
12
#10000
0$
#15000
b1 !
b1 1
0-
1$
#16000
0&
b100 )
b11010000110010101111000001000000111010001110010011101010111010001101000001000000111010001100001011000100110110001100101 3
#20000
0$
#25000
1$
#26000
1&
b101 )
b110010101101110011000010110001001101100011001010010000001111010011001010111001001101111001000000110100001101111011011000110010001110011001000000110000101100011011101000110100101110110011001010010000001110011011011000110111101110100 3
#30000
0$
#35000
b1100000 "
b1100000 0
b0 !
b0 1
b1 /
b1 #
b1 .
1-
1$
#36000
0&
b110 )
b1100010011011000110000101101110011010110010000001101001011011100111010001100101011100100111011001100001011011000010000001100010011001010111010001110111011001010110010101101110001000000110010101110110011001010111001001111001001000000110010001101001011001110110100101110100 3
#40000
0$
#45000
1$
#46000
1&
b1 +
b111 )
b1100010011011000110000101101110011010110010000001101001011011100111010001100101011100100111011001100001011011000010000001101000011011110110110001100100 3
#50000
0$
#55000
b10 !
b10 1
0-
1$
#56000
0&
b1010 )
b11010000110010101111000001000000111010001110010011101010111010001101000001000000111010001100001011000100110110001100101 3
#60000
0$
#65000
1$
#66000
1&
b1011 )
b110010101101110011000010110001001101100011001010010000001111010011001010111001001101111001000000110100001101111011011000110010001110011001000000110000101100011011101000110100101110110011001010010000001110011011011000110111101110100 3
#70000
0$
#75000
b11011010 "
b11011010 0
b0 !
b0 1
b10 /
b10 #
b10 .
1-
1$
#76000
0&
b1100 )
b1100010011011000110000101101110011010110010000001101001011011100111010001100101011100100111011001100001011011000010000001100010011001010111010001110111011001010110010101101110001000000110010101110110011001010111001001111001001000000110010001101001011001110110100101110100 3
#80000
0$
#85000
1$
#86000
1&
b10 +
b1101 )
b1100010011011000110000101101110011010110010000001101001011011100111010001100101011100100111011001100001011011000010000001101000011011110110110001100100 3
#90000
0$
#95000
b100 !
b100 1
0-
1$
#96000
0&
b10000 )
b11010000110010101111000001000000111010001110010011101010111010001101000001000000111010001100001011000100110110001100101 3
#100000
0$
#105000
1$
#106000
1&
b10001 )
b110010101101110011000010110001001101100011001010010000001111010011001010111001001101111001000000110100001101111011011000110010001110011001000000110000101100011011101000110100101110110011001010010000001110011011011000110111101110100 3
#110000
0$
#115000
b11110010 "
b11110010 0
b0 !
b0 1
b11 /
b11 #
b11 .
1-
1$
#116000
0&
b10010 )
b1100010011011000110000101101110011010110010000001101001011011100111010001100101011100100111011001100001011011000010000001100010011001010111010001110111011001010110010101101110001000000110010101110110011001010111001001111001001000000110010001101001011001110110100101110100 3
#120000
0$
#125000
1$
#126000
1&
b11 +
b10011 )
b1100010011011000110000101101110011010110010000001101001011011100111010001100101011100100111011001100001011011000010000001101000011011110110110001100100 3
#130000
0$
#135000
b1000 !
b1000 1
0-
1$
#136000
0&
b10110 )
b11010000110010101111000001000000111010001110010011101010111010001101000001000000111010001100001011000100110110001100101 3
#140000
0$
#145000
1$
#146000
1&
b10111 )
b110010101101110011000010110001001101100011001010010000001111010011001010111001001101111001000000110100001101111011011000110010001110011001000000110000101100011011101000110100101110110011001010010000001110011011011000110111101110100 3
#150000
0$
#155000
b1100110 "
b1100110 0
b0 !
b0 1
b100 /
b100 #
b100 .
1-
1$
#156000
0&
b11000 )
b1100010011011000110000101101110011010110010000001101001011011100111010001100101011100100111011001100001011011000010000001100010011001010111010001110111011001010110010101101110001000000110010101110110011001010111001001111001001000000110010001101001011001110110100101110100 3
#160000
0$
#165000
1$
#166000
1&
b100 +
b11001 )
b1100010011011000110000101101110011010110010000001101001011011100111010001100101011100100111011001100001011011000010000001101000011011110110110001100100 3
#170000
0$
#175000
b10000 !
b10000 1
0-
1$
#176000
0&
b11100 )
b11010000110010101111000001000000111010001110010011101010111010001101000001000000111010001100001011000100110110001100101 3
#180000
0$
#185000
1$
#186000
1&
b11101 )
b110010101101110011000010110001001101100011001010010000001111010011001010111001001101111001000000110100001101111011011000110010001110011001000000110000101100011011101000110100101110110011001010010000001110011011011000110111101110100 3
#190000
0$
#195000
b10110110 "
b10110110 0
b0 !
b0 1
b101 /
b101 #
b101 .
1-
1$
#196000
0&
b11110 )
b1100010011011000110000101101110011010110010000001101001011011100111010001100101011100100111011001100001011011000010000001100010011001010111010001110111011001010110010101101110001000000110010101110110011001010111001001111001001000000110010001101001011001110110100101110100 3
#200000
0$
#205000
1$
#206000
1&
b101 +
b11111 )
b1100010011011000110000101101110011010110010000001101001011011100111010001100101011100100111011001100001011011000010000001101000011011110110110001100100 3
#210000
0$
#215000
b100000 !
b100000 1
0-
1$
#216000
0&
b100010 )
b11010000110010101111000001000000111010001110010011101010111010001101000001000000111010001100001011000100110110001100101 3
#220000
0$
#225000
1$
#226000
1&
b100011 )
b110010101101110011000010110001001101100011001010010000001111010011001010111001001101111001000000110100001101111011011000110010001110011001000000110000101100011011101000110100101110110011001010010000001110011011011000110111101110100 3
#230000
0$
#235000
b10111110 "
b10111110 0
b0 !
b0 1
b110 /
b110 #
b110 .
1-
1$
#236000
0&
b100100 )
b1100010011011000110000101101110011010110010000001101001011011100111010001100101011100100111011001100001011011000010000001100010011001010111010001110111011001010110010101101110001000000110010101110110011001010111001001111001001000000110010001101001011001110110100101110100 3
#240000
0$
#245000
1$
#246000
1&
b110 +
b100101 )
b1100010011011000110000101101110011010110010000001101001011011100111010001100101011100100111011001100001011011000010000001101000011011110110110001100100 3
#250000
0$
#255000
b1000000 !
b1000000 1
0-
1$
#256000
0&
b101000 )
b11010000110010101111000001000000111010001110010011101010111010001101000001000000111010001100001011000100110110001100101 3
#260000
0$
#265000
1$
#266000
1&
b101001 )
b110010101101110011000010110001001101100011001010010000001111010011001010111001001101111001000000110100001101111011011000110010001110011001000000110000101100011011101000110100101110110011001010010000001110011011011000110111101110100 3
#270000
0$
#275000
b11100000 "
b11100000 0
b0 !
b0 1
b111 /
b111 #
b111 .
1-
1$
#276000
0&
b101010 )
b1100010011011000110000101101110011010110010000001101001011011100111010001100101011100100111011001100001011011000010000001100010011001010111010001110111011001010110010101101110001000000110010101110110011001010111001001111001001000000110010001101001011001110110100101110100 3
#280000
0$
#285000
1$
#286000
1&
b111 +
b101011 )
b1100010011011000110000101101110011010110010000001101001011011100111010001100101011100100111011001100001011011000010000001101000011011110110110001100100 3
#290000
0$
#295000
b10000000 !
b10000000 1
0-
1$
#296000
0&
b101110 )
b11010000110010101111000001000000111010001110010011101010111010001101000001000000111010001100001011000100110110001100101 3
#300000
0$
#305000
1$
#306000
1&
b101111 )
b110010101101110011000010110001001101100011001010010000001111010011001010111001001101111001000000110100001101111011011000110010001110011001000000110000101100011011101000110100101110110011001010010000001110011011011000110111101110100 3
#310000
0$
#315000
b11111100 "
b11111100 0
b0 !
b0 1
b0 /
b0 #
b0 .
1-
1$
#316000
0&
b110000 )
b1100010011011000110000101101110011010110010000001101001011011100111010001100101011100100111011001100001011011000010000001100010011001010111010001110111011001010110010101101110001000000110010101110110011001010111001001111001001000000110010001101001011001110110100101110100 3
#320000
0$
#325000
1$
#326000
1&
b1 *
b0 +
b110001 )
b1100010011011000110000101101110011010110010000001101001011011100111010001100101011100100111011001100001011011000010000001101000011011110110110001100100 3
#330000
0$
#335000
b1 !
b1 1
0-
1$
#336000
0&
b110100 )
b11010000110010101111000001000000111010001110010011101010111010001101000001000000111010001100001011000100110110001100101 3
#340000
0$
#345000
1$
#346000
1&
b110101 )
b110010101101110011000010110001001101100011001010010000001111010011001010111001001101111001000000110100001101111011011000110010001110011001000000110000101100011011101000110100101110110011001010010000001110011011011000110111101110100 3
#350000
0$
#355000
b1100000 "
b1100000 0
b0 !
b0 1
b1 /
b1 #
b1 .
1-
1$
#356000
0&
b110110 )
b1100010011011000110000101101110011010110010000001101001011011100111010001100101011100100111011001100001011011000010000001100010011001010111010001110111011001010110010101101110001000000110010101110110011001010111001001111001001000000110010001101001011001110110100101110100 3
#360000
0$
#365000
1$
#366000
1&
b1 +
b110111 )
b1100010011011000110000101101110011010110010000001101001011011100111010001100101011100100111011001100001011011000010000001101000011011110110110001100100 3
#370000
0$
#375000
b10 !
b10 1
0-
1$
#376000
0&
b111010 )
b11010000110010101111000001000000111010001110010011101010111010001101000001000000111010001100001011000100110110001100101 3
#380000
0$
#385000
1$
#386000
1&
b111011 )
b110010101101110011000010110001001101100011001010010000001111010011001010111001001101111001000000110100001101111011011000110010001110011001000000110000101100011011101000110100101110110011001010010000001110011011011000110111101110100 3
#390000
0$
#395000
b11011010 "
b11011010 0
b0 !
b0 1
b10 /
b10 #
b10 .
1-
1$
#396000
0&
b111100 )
b1100010011011000110000101101110011010110010000001101001011011100111010001100101011100100111011001100001011011000010000001100010011001010111010001110111011001010110010101101110001000000110010101110110011001010111001001111001001000000110010001101001011001110110100101110100 3
#400000
0$
#405000
1$
#406000
1&
b10 +
b111101 )
b1100010011011000110000101101110011010110010000001101001011011100111010001100101011100100111011001100001011011000010000001101000011011110110110001100100 3
#410000
0$
#415000
b100 !
b100 1
0-
1$
#416000
0&
b1000000 )
b11010000110010101111000001000000111010001110010011101010111010001101000001000000111010001100001011000100110110001100101 3
#420000
0$
#425000
1$
#426000
1&
b1000001 )
b110010101101110011000010110001001101100011001010010000001111010011001010111001001101111001000000110100001101111011011000110010001110011001000000110000101100011011101000110100101110110011001010010000001110011011011000110111101110100 3
#430000
0$
#435000
b11110010 "
b11110010 0
b0 !
b0 1
b11 /
b11 #
b11 .
1-
1$
#436000
0&
b1000010 )
b1100010011011000110000101101110011010110010000001101001011011100111010001100101011100100111011001100001011011000010000001100010011001010111010001110111011001010110010101101110001000000110010101110110011001010111001001111001001000000110010001101001011001110110100101110100 3
#440000
0$
#445000
1$
#446000
1&
b11 +
b1000011 )
b1100010011011000110000101101110011010110010000001101001011011100111010001100101011100100111011001100001011011000010000001101000011011110110110001100100 3
#450000
0$
#455000
b1000 !
b1000 1
0-
1$
#456000
0&
b1000110 )
b11010000110010101111000001000000111010001110010011101010111010001101000001000000111010001100001011000100110110001100101 3
#460000
0$
#465000
1$
#466000
1&
b1000111 )
b110010101101110011000010110001001101100011001010010000001111010011001010111001001101111001000000110100001101111011011000110010001110011001000000110000101100011011101000110100101110110011001010010000001110011011011000110111101110100 3
#470000
0$
#475000
b1100110 "
b1100110 0
b0 !
b0 1
b100 /
b100 #
b100 .
1-
1$
#476000
0&
b1001000 )
b1100010011011000110000101101110011010110010000001101001011011100111010001100101011100100111011001100001011011000010000001100010011001010111010001110111011001010110010101101110001000000110010101110110011001010111001001111001001000000110010001101001011001110110100101110100 3
#480000
0$
#485000
1$
#486000
1&
b100 +
b1001001 )
b1100010011011000110000101101110011010110010000001101001011011100111010001100101011100100111011001100001011011000010000001101000011011110110110001100100 3
#490000
0$
#495000
b10000 !
b10000 1
0-
1$
#496000
0&
b1001100 )
b11010000110010101111000001000000111010001110010011101010111010001101000001000000111010001100001011000100110110001100101 3
#500000
0$
#505000
1$
#506000
1&
b1001101 )
b110010101101110011000010110001001101100011001010010000001111010011001010111001001101111001000000110100001101111011011000110010001110011001000000110000101100011011101000110100101110110011001010010000001110011011011000110111101110100 3
#510000
0$
#515000
b10110110 "
b10110110 0
b0 !
b0 1
b101 /
b101 #
b101 .
1-
1$
#516000
0&
b1001110 )
b1100010011011000110000101101110011010110010000001101001011011100111010001100101011100100111011001100001011011000010000001100010011001010111010001110111011001010110010101101110001000000110010101110110011001010111001001111001001000000110010001101001011001110110100101110100 3
#520000
0$
#525000
1$
#526000
1&
b101 +
b1001111 )
b1100010011011000110000101101110011010110010000001101001011011100111010001100101011100100111011001100001011011000010000001101000011011110110110001100100 3
#530000
0$
#535000
b100000 !
b100000 1
0-
1$
#536000
0&
b1010010 )
b11010000110010101111000001000000111010001110010011101010111010001101000001000000111010001100001011000100110110001100101 3
#540000
0$
#545000
1$
#546000
1&
b1010011 )
b110010101101110011000010110001001101100011001010010000001111010011001010111001001101111001000000110100001101111011011000110010001110011001000000110000101100011011101000110100101110110011001010010000001110011011011000110111101110100 3
#550000
0$
#555000
b10111110 "
b10111110 0
b0 !
b0 1
b110 /
b110 #
b110 .
1-
1$
#556000
0&
b1010100 )
b1100010011011000110000101101110011010110010000001101001011011100111010001100101011100100111011001100001011011000010000001100010011001010111010001110111011001010110010101101110001000000110010101110110011001010111001001111001001000000110010001101001011001110110100101110100 3
#560000
0$
#565000
1$
#566000
1&
b110 +
b1010101 )
b1100010011011000110000101101110011010110010000001101001011011100111010001100101011100100111011001100001011011000010000001101000011011110110110001100100 3
#570000
0$
#575000
b1000000 !
b1000000 1
0-
1$
#576000
0&
b1011000 )
b11010000110010101111000001000000111010001110010011101010111010001101000001000000111010001100001011000100110110001100101 3
#580000
0$
#585000
1$
#586000
1&
b1011001 )
b110010101101110011000010110001001101100011001010010000001111010011001010111001001101111001000000110100001101111011011000110010001110011001000000110000101100011011101000110100101110110011001010010000001110011011011000110111101110100 3
#590000
0$
#595000
b11100000 "
b11100000 0
b0 !
b0 1
b111 /
b111 #
b111 .
1-
1$
#596000
0&
b1011010 )
b1100010011011000110000101101110011010110010000001101001011011100111010001100101011100100111011001100001011011000010000001100010011001010111010001110111011001010110010101101110001000000110010101110110011001010111001001111001001000000110010001101001011001110110100101110100 3
#600000
0$
#605000
1$
#606000
1&
b111 +
b1011011 )
b1100010011011000110000101101110011010110010000001101001011011100111010001100101011100100111011001100001011011000010000001101000011011110110110001100100 3
#610000
0$
#615000
b10000000 !
b10000000 1
0-
1$
#616000
0&
b1011110 )
b11010000110010101111000001000000111010001110010011101010111010001101000001000000111010001100001011000100110110001100101 3
#620000
0$
#625000
1$
#626000
1&
b1011111 )
b110010101101110011000010110001001101100011001010010000001111010011001010111001001101111001000000110100001101111011011000110010001110011001000000110000101100011011101000110100101110110011001010010000001110011011011000110111101110100 3
#630000
0$
#635000
b11111100 "
b11111100 0
b0 !
b0 1
b0 /
b0 #
b0 .
1-
1$
#636000
0&
b1100000 )
b1100010011011000110000101101110011010110010000001101001011011100111010001100101011100100111011001100001011011000010000001100010011001010111010001110111011001010110010101101110001000000110010101110110011001010111001001111001001000000110010001101001011001110110100101110100 3
#640000
0$
#645000
1$
#646000
b11111110 "
b11111110 0
b1000 /
1&
b11111110110111001011101010011000 %
b11111110110111001011101010011000 ,
b1 (
b0 *
b0 +
b1100001 )
b1100010011011000110000101101110011010110010000001101001011011100111010001100101011100100111011001100001011011000010000001101000011011110110110001100100 3
#650000
0$
#655000
b1 !
b1 1
0-
1$
#656000
0&
b1100100 )
b11010000110010101111000001000000111010001110010011101010111010001101000001000000111010001100001011000100110110001100101 3
#660000
0$
#665000
1$
#666000
1&
b1100101 )
b110010101101110011000010110001001101100011001010010000001111010011001010111001001101111001000000110100001101111011011000110010001110011001000000110000101100011011101000110100101110110011001010010000001110011011011000110111101110100 3
#670000
0$
#675000
b11110110 "
b11110110 0
b0 !
b0 1
b1001 /
b1 #
b1 .
1-
1$
#676000
0&
b1100110 )
b1100010011011000110000101101110011010110010000001101001011011100111010001100101011100100111011001100001011011000010000001100010011001010111010001110111011001010110010101101110001000000110010101110110011001010111001001111001001000000110010001101001011001110110100101110100 3
#680000
0$
#685000
1$
#686000
1&
b1 +
b1100111 )
b1100010011011000110000101101110011010110010000001101001011011100111010001100101011100100111011001100001011011000010000001101000011011110110110001100100 3
#690000
0$
#695000
b10 !
b10 1
0-
1$
#696000
0&
b1101010 )
b11010000110010101111000001000000111010001110010011101010111010001101000001000000111010001100001011000100110110001100101 3
#700000
0$
#705000
1$
#706000
1&
b1101011 )
b110010101101110011000010110001001101100011001010010000001111010011001010111001001101111001000000110100001101111011011000110010001110011001000000110000101100011011101000110100101110110011001010010000001110011011011000110111101110100 3
#710000
0$
#715000
b11101110 "
b11101110 0
b0 !
b0 1
b1010 /
b10 #
b10 .
1-
1$
#716000
0&
b1101100 )
b1100010011011000110000101101110011010110010000001101001011011100111010001100101011100100111011001100001011011000010000001100010011001010111010001110111011001010110010101101110001000000110010101110110011001010111001001111001001000000110010001101001011001110110100101110100 3
#720000
0$
#725000
1$
#726000
1&
b10 +
b1101101 )
b1100010011011000110000101101110011010110010000001101001011011100111010001100101011100100111011001100001011011000010000001101000011011110110110001100100 3
#730000
0$
#735000
b100 !
b100 1
0-
1$
#736000
0&
b1110000 )
b11010000110010101111000001000000111010001110010011101010111010001101000001000000111010001100001011000100110110001100101 3
#740000
0$
#745000
1$
#746000
1&
b1110001 )
b110010101101110011000010110001001101100011001010010000001111010011001010111001001101111001000000110100001101111011011000110010001110011001000000110000101100011011101000110100101110110011001010010000001110011011011000110111101110100 3
#750000
0$
#755000
b111110 "
b111110 0
b0 !
b0 1
b1011 /
b11 #
b11 .
1-
1$
#756000
0&
b1110010 )
b1100010011011000110000101101110011010110010000001101001011011100111010001100101011100100111011001100001011011000010000001100010011001010111010001110111011001010110010101101110001000000110010101110110011001010111001001111001001000000110010001101001011001110110100101110100 3
#760000
0$
#765000
1$
#766000
1&
b11 +
b1110011 )
b1100010011011000110000101101110011010110010000001101001011011100111010001100101011100100111011001100001011011000010000001101000011011110110110001100100 3
#770000
0$
#775000
b1000 !
b1000 1
0-
1$
#776000
0&
b1110110 )
b11010000110010101111000001000000111010001110010011101010111010001101000001000000111010001100001011000100110110001100101 3
#780000
0$
#785000
1$
#786000
1&
b1110111 )
b110010101101110011000010110001001101100011001010010000001111010011001010111001001101111001000000110100001101111011011000110010001110011001000000110000101100011011101000110100101110110011001010010000001110011011011000110111101110100 3
#790000
0$
#795000
b10011100 "
b10011100 0
b0 !
b0 1
b1100 /
b100 #
b100 .
1-
1$
#796000
0&
b1111000 )
b1100010011011000110000101101110011010110010000001101001011011100111010001100101011100100111011001100001011011000010000001100010011001010111010001110111011001010110010101101110001000000110010101110110011001010111001001111001001000000110010001101001011001110110100101110100 3
#800000
0$
#805000
1$
#806000
1&
b100 +
b1111001 )
b1100010011011000110000101101110011010110010000001101001011011100111010001100101011100100111011001100001011011000010000001101000011011110110110001100100 3
#810000
0$
#815000
b10000 !
b10000 1
0-
1$
#816000
0&
b1111100 )
b11010000110010101111000001000000111010001110010011101010111010001101000001000000111010001100001011000100110110001100101 3
#820000
0$
#825000
1$
#826000
1&
b1111101 )
b110010101101110011000010110001001101100011001010010000001111010011001010111001001101111001000000110100001101111011011000110010001110011001000000110000101100011011101000110100101110110011001010010000001110011011011000110111101110100 3
#830000
0$
#835000
b1111010 "
b1111010 0
b0 !
b0 1
b1101 /
b101 #
b101 .
1-
1$
#836000
0&
b1111110 )
b1100010011011000110000101101110011010110010000001101001011011100111010001100101011100100111011001100001011011000010000001100010011001010111010001110111011001010110010101101110001000000110010101110110011001010111001001111001001000000110010001101001011001110110100101110100 3
#840000
0$
#845000
1$
#846000
1&
b101 +
b1111111 )
b1100010011011000110000101101110011010110010000001101001011011100111010001100101011100100111011001100001011011000010000001101000011011110110110001100100 3
#850000
0$
#855000
b100000 !
b100000 1
0-
1$
#856000
0&
b10000010 )
b11010000110010101111000001000000111010001110010011101010111010001101000001000000111010001100001011000100110110001100101 3
#860000
0$
#865000
1$
#866000
1&
b10000011 )
b110010101101110011000010110001001101100011001010010000001111010011001010111001001101111001000000110100001101111011011000110010001110011001000000110000101100011011101000110100101110110011001010010000001110011011011000110111101110100 3
#870000
0$
#875000
b10011110 "
b10011110 0
b0 !
b0 1
b1110 /
b110 #
b110 .
1-
1$
#876000
0&
b10000100 )
b1100010011011000110000101101110011010110010000001101001011011100111010001100101011100100111011001100001011011000010000001100010011001010111010001110111011001010110010101101110001000000110010101110110011001010111001001111001001000000110010001101001011001110110100101110100 3
#880000
0$
#885000
1$
#886000
1&
b110 +
b10000101 )
b1100010011011000110000101101110011010110010000001101001011011100111010001100101011100100111011001100001011011000010000001101000011011110110110001100100 3
#890000
0$
#895000
b1000000 !
b1000000 1
0-
1$
#896000
0&
b10001000 )
b11010000110010101111000001000000111010001110010011101010111010001101000001000000111010001100001011000100110110001100101 3
#900000
0$
#905000
1$
#906000
1&
b10001001 )
b110010101101110011000010110001001101100011001010010000001111010011001010111001001101111001000000110100001101111011011000110010001110011001000000110000101100011011101000110100101110110011001010010000001110011011011000110111101110100 3
#910000
0$
#915000
b10001110 "
b10001110 0
b0 !
b0 1
b1111 /
b111 #
b111 .
1-
1$
#916000
0&
b10001010 )
b1100010011011000110000101101110011010110010000001101001011011100111010001100101011100100111011001100001011011000010000001100010011001010111010001110111011001010110010101101110001000000110010101110110011001010111001001111001001000000110010001101001011001110110100101110100 3
#920000
0$
#925000
1$
#926000
1&
b111 +
b10001011 )
b1100010011011000110000101101110011010110010000001101001011011100111010001100101011100100111011001100001011011000010000001101000011011110110110001100100 3
#930000
0$
#935000
b10000000 !
b10000000 1
0-
1$
#936000
0&
b10001110 )
b11010000110010101111000001000000111010001110010011101010111010001101000001000000111010001100001011000100110110001100101 3
#940000
0$
#945000
1$
#946000
1&
b10001111 )
b110010101101110011000010110001001101100011001010010000001111010011001010111001001101111001000000110100001101111011011000110010001110011001000000110000101100011011101000110100101110110011001010010000001110011011011000110111101110100 3
#950000
0$
#955000
b11111110 "
b11111110 0
b0 !
b0 1
b1000 /
b0 #
b0 .
1-
1$
#956000
0&
b10010000 )
b1100010011011000110000101101110011010110010000001101001011011100111010001100101011100100111011001100001011011000010000001100010011001010111010001110111011001010110010101101110001000000110010101110110011001010111001001111001001000000110010001101001011001110110100101110100 3
#960000
0$
#965000
1$
#966000
1&
b1 *
b0 +
b10010001 )
b1100010011011000110000101101110011010110010000001101001011011100111010001100101011100100111011001100001011011000010000001101000011011110110110001100100 3
#970000
0$
#975000
b1 !
b1 1
0-
1$
#976000
0&
b10010100 )
b11010000110010101111000001000000111010001110010011101010111010001101000001000000111010001100001011000100110110001100101 3
#980000
0$
#985000
1$
#986000
1&
b10010101 )
b110010101101110011000010110001001101100011001010010000001111010011001010111001001101111001000000110100001101111011011000110010001110011001000000110000101100011011101000110100101110110011001010010000001110011011011000110111101110100 3
#990000
0$
#995000
b11110110 "
b11110110 0
b0 !
b0 1
b1001 /
b1 #
b1 .
1-
1$
#996000
0&
b10010110 )
b1100010011011000110000101101110011010110010000001101001011011100111010001100101011100100111011001100001011011000010000001100010011001010111010001110111011001010110010101101110001000000110010101110110011001010111001001111001001000000110010001101001011001110110100101110100 3
#1000000
0$
#1005000
1$
#1006000
1&
b1 +
b10010111 )
b1100010011011000110000101101110011010110010000001101001011011100111010001100101011100100111011001100001011011000010000001101000011011110110110001100100 3
#1010000
0$
#1015000
b10 !
b10 1
0-
1$
#1016000
0&
b10011010 )
b11010000110010101111000001000000111010001110010011101010111010001101000001000000111010001100001011000100110110001100101 3
#1020000
0$
#1025000
1$
#1026000
1&
b10011011 )
b110010101101110011000010110001001101100011001010010000001111010011001010111001001101111001000000110100001101111011011000110010001110011001000000110000101100011011101000110100101110110011001010010000001110011011011000110111101110100 3
#1030000
0$
#1035000
b11101110 "
b11101110 0
b0 !
b0 1
b1010 /
b10 #
b10 .
1-
1$
#1036000
0&
b10011100 )
b1100010011011000110000101101110011010110010000001101001011011100111010001100101011100100111011001100001011011000010000001100010011001010111010001110111011001010110010101101110001000000110010101110110011001010111001001111001001000000110010001101001011001110110100101110100 3
#1040000
0$
#1045000
1$
#1046000
1&
b10 +
b10011101 )
b1100010011011000110000101101110011010110010000001101001011011100111010001100101011100100111011001100001011011000010000001101000011011110110110001100100 3
#1050000
0$
#1055000
b100 !
b100 1
0-
1$
#1056000
0&
b10100000 )
b11010000110010101111000001000000111010001110010011101010111010001101000001000000111010001100001011000100110110001100101 3
#1060000
0$
#1065000
1$
#1066000
1&
b10100001 )
b110010101101110011000010110001001101100011001010010000001111010011001010111001001101111001000000110100001101111011011000110010001110011001000000110000101100011011101000110100101110110011001010010000001110011011011000110111101110100 3
#1070000
0$
#1075000
b111110 "
b111110 0
b0 !
b0 1
b1011 /
b11 #
b11 .
1-
1$
#1076000
0&
b10100010 )
b1100010011011000110000101101110011010110010000001101001011011100111010001100101011100100111011001100001011011000010000001100010011001010111010001110111011001010110010101101110001000000110010101110110011001010111001001111001001000000110010001101001011001110110100101110100 3
#1080000
0$
#1085000
1$
#1086000
1&
b11 +
b10100011 )
b1100010011011000110000101101110011010110010000001101001011011100111010001100101011100100111011001100001011011000010000001101000011011110110110001100100 3
#1090000
0$
#1095000
b1000 !
b1000 1
0-
1$
#1096000
0&
b10100110 )
b11010000110010101111000001000000111010001110010011101010111010001101000001000000111010001100001011000100110110001100101 3
#1100000
0$
#1105000
1$
#1106000
1&
b10100111 )
b110010101101110011000010110001001101100011001010010000001111010011001010111001001101111001000000110100001101111011011000110010001110011001000000110000101100011011101000110100101110110011001010010000001110011011011000110111101110100 3
#1110000
0$
#1115000
b10011100 "
b10011100 0
b0 !
b0 1
b1100 /
b100 #
b100 .
1-
1$
